flannel/__init__.py
flannel/json_output.py
flannel/main.py
flannel-1.2.dist-info/DESCRIPTION.rst
flannel-1.2.dist-info/METADATA
flannel-1.2.dist-info/RECORD
flannel-1.2.dist-info/WHEEL
flannel-1.2.dist-info/entry_points.txt
flannel-1.2.dist-info/metadata.json
flannel-1.2.dist-info/top_level.txt
