Metadata-Version: 2.0
Name: flannel
Version: 1.2
Summary: Flannel \| A JSON Log Reader
Requires-Dist: pyyaml
Requires-Dist: dpath (==1.4.2)
Requires-Dist: pyqt5
